toyama/api.py
toyama/device.py
toyama/gateway.py
toyama/logger.py
toyama-0.1.0.dist-info/METADATA
toyama-0.1.0.dist-info/WHEEL
toyama-0.1.0.dist-info/RECORD
