Metadata-Version: 2.1
Name: toyama
Version: 0.1.0
Summary: API wrapper for Toyama Switch Controlls
Author: Prasanna Reddy
Author-email: prasannareddy_ch@outlook.com
Requires-Python: >=3.12,<3.14
Classifier: Programming Language :: Python :: 3
Classifier: Programming Language :: Python :: 3.12
Classifier: Programming Language :: Python :: 3.13
Requires-Dist: aiohttp (>=3.11.11,<4.0.0)
Requires-Dist: loguru (>=0.7.3,<0.8.0)
Requires-Dist: zeroconf (>=0.136.2,<0.137.0)
